cubicweb_celerytask/__init__.py
cubicweb_celerytask/__pkginfo__.py
cubicweb_celerytask/ccplugin.py
cubicweb_celerytask/entities.py
cubicweb_celerytask/hooks.py
cubicweb_celerytask/schema.py
cubicweb_celerytask/site_cubicweb.py
cubicweb_celerytask/testutils.py
cubicweb_celerytask/views.py
cubicweb_celerytask/data/cubes.celerytask.js
cubicweb_celerytask/i18n/en.po
cubicweb_celerytask/i18n/fr.po
cubicweb_celerytask/migration/0.4.0_Any.py
cubicweb_celerytask/migration/0.6.0_Any.py
cubicweb_celerytask/migration/__init__.py
cubicweb_celerytask/migration/postcreate.py
cubicweb_celerytask/migration/utils.py
cubicweb_celerytask-2.0.2.dist-info/METADATA
cubicweb_celerytask-2.0.2.dist-info/WHEEL
cubicweb_celerytask-2.0.2.dist-info/entry_points.txt
cubicweb_celerytask-2.0.2.dist-info/top_level.txt
cubicweb_celerytask-2.0.2.dist-info/RECORD
