Metadata-Version: 2.1
Name: cubicweb-celerytask
Version: 2.0.2
Summary: Run and monitor celery tasks
Home-page: https://forge.extranet.logilab.fr/cubicweb/cubes/cubicweb-celerytask
Author: LOGILAB S.A. (Paris, FRANCE)
Author-email: contact@logilab.fr
License: LGPL
Classifier: Environment :: Web Environment
Classifier: Framework :: CubicWeb
Classifier: Programming Language :: Python
Classifier: Programming Language :: Python :: 3
Classifier: Programming Language :: Python :: 3 :: Only
Classifier: Programming Language :: JavaScript
Requires-Python: >=3.9.2
Requires-Dist: celery~=5.0
Requires-Dist: cubicweb<5.0.0,>=4.5.2
Requires-Dist: cw-celerytask-helpers>=0.11.0
